Workbook

Sheet Home
A1: McDonald's Financial Forecast Project
A2: 2014-2018 Historical data and 5-year Annual forecast.
A4: Prepared by: | B4: Pranav. J
A5: Date: | B5: 11th of March, 2025
A6: Purpose: | B6: Financial Analysis and Forecasting
A17: Sl. No. | B17: Section | C17: Description | D17: Link
A18: 1 | B18: Overview | C18: Historical Income data summary. | D18: Go to Overview
A19: 2 | B19: Balance sheet | C19: Assests, Liabilities and Equity. | D19: Go to Balance Sheet
A20: 3 | B20: Cash Flow(CF) Statement | C20: Cash inflows and outflows. | D20: Go to CF Statemant
A21: 4 | B21: Ratio Analysis | C21: Profitability and leverage ratios. | D21: Go to Ratios
A22: 5 | B22: Segment Analysis | C22: Segment-wise revenue. | D22: Go to Segement Analysis
A23: 6 | B23: Quarterly Data | C23: Quarterly revenues, seasonality, volatility, Cycles. | D23: Go to Quarterly Data
A24: 7 | B24: Market Research | C24: Market research for industry and markets. | D24: Go to Market Research
A25: 8 | B25: Assumed growth | C25: Assumed growth of markets and segments. | D25: Go to Assumed growth
A26: 9 | B26: Forecast | C26: 5 year forecast of company. | D26: Go to Forecast
A27: 10 | B27: References | C27: References. | D27: Go to References
A28: 11 | B28: Summary | C28: Summary. | D28: Go to Summary
A29: 12 | B29: Outcome Analysis | C29: Comparing forecast with actual data. | D29: Go to Outcome Analysis
A30: 13 | B30: Conlusion | C30: Conclusion | D30: Go to Outcome Analysis

Sheet Overview
A1: Income Sheet Overview
A2: Go to Home
A3: In millions, except share data, (10-K)
A4: All values in 2018 USD (BLS CPI-U Adjusted)
A5: Metrics | B5: Year | G5: CAGR | I5: Metrics | J5: Years
B6: 2014 | C6: 2015 | D6: 2016 | E6: 2017 | F6: 2018 | J6: 2014 | K6: 2015 | L6: 2016 | M6: 2017 | N6: 2018
A7: Revenues | I7: Revenue growth | J7: - | K7: =C11 -> -0.075012075 | L7: =D11 -> -0.043199893 | M7: =E11 -> -0.092499548 | N7: =F11 -> -0.10063328
A8: Sales by Company-operated restaurants | B8: 19272.263 | C8: 17468.166 | D8: 16002.373 | E8: 13029.556 | F8: 10012.7 | G8: =(((F8/B8)^(0.2))-1)*100% -> -0.12274935 | I8: EPS growth | J8: - | K8: =C27 -> -0.0039138943 | L8: =D27 -> 0.11787819 | M8: =E27 -> 0.14762742 | N8: =F27 -> 0.15467075
A9: Revenues from franchised restaurants | B9: 9834.8545 | C9: 9455.5664 | D9: 9758.2565 | E9: 10348.227 | F9: 11012.5 | G9: =(((F9/B9)^(0.2))-1)*100% -> 0.022877432 | I9: Operating margin | J9: =B19 -> 0.28967287 | K9: =C19 -> 0.28119466 | L9: =D19 -> 0.31453706 | M9: =E19 -> 0.41860353 | N9: =F19 -> 0.41962027
A10: Total revenues | B10: =SUM(B8:B9) -> 29107.117 | C10: =SUM(C8:C9) -> 26923.732 | D10: =SUM(D8:D9) -> 25760.63 | E10: =SUM(E8:E9) -> 23377.783 | F10: =SUM(F8:F9) -> 21025.2 | G10: =(((F10/B10)^(0.2))-1)*100% -> -0.062981451 | I10: Net margin | J10: =B25 -> 0.17338829 | K10: =C25 -> 0.17821587 | L10: =D25 -> 0.19033868 | M10: =E25 -> 0.22752888 | N10: =F25 -> 0.2817714
A11: Revenue growth | B11: - | C11: =((C10-B10)/B10)*100% -> -0.075012075 | D11: =((D10-C10)/C10)*100% -> -0.043199893 | E11: =((E10-D10)/D10)*100% -> -0.092499548 | F11: =((F10-E10)/E10)*100% -> -0.10063328
A12: Operating costs and expenses
A13: Company operated expenses | B13: 16216.054 | C13: 14807.894 | D13: 13286.102 | E13: 10663.852 | F13: =3153.8+2937.9+2174.2 -> 8265.9 | G13: =(((F13/B13)^(0.2))-1)*100% -> -0.12608541
A14: Franchised expenses | B14: 1800.016 | C14: 1744.9096 | D14: 1797.8737 | E14: 1833.7203 | F14: 1973.3 | G14: =(((F14/B14)^(0.2))-1)*100% -> 0.018552342
A15: Selling, general & administrative expenses | B15: 2639.0334 | C15: 2578.6945 | D15: 2494.7799 | E15: 2285.799 | F15: 2200.2 | G15: =(((F15/B15)^(0.2))-1)*100% -> -0.035719345
A16: Others | B16: 20.15339 | C16: 221.42447 | D16: 79.201023 | E16: -1191.6109 | F16: -236.8 | G16: =(((F16/B16)^(0.2))-1)*100% -> -2.6368418
A17: Toatal operating costs and expenses | B17: =SUM(B13:B16) -> 20675.257 | C17: =SUM(C13:C16) -> 19352.922 | D17: =SUM(D13:D16) -> 17657.957 | E17: =SUM(E13:E16) -> 13591.761 | F17: =SUM(F13:F16) -> 12202.6 | G17: =(((F17/B17)^(0.2))-1)*100% -> -0.10008748
A18: Operating income | B18: 8431.5421 | C18: 7570.8098 | D18: 8102.6727 | E18: 9786.0225 | F18: 8822.6 | G18: =(((F18/B18)^(0.2))-1)*100% -> 0.0091086192
A19: Operating margin | B19: =(B18/B10)*100% -> 0.28967287 | C19: =(C18/C10)*100% -> 0.28119466 | D19: =(D18/D10)*100% -> 0.31453706 | E19: =(E18/E10)*100% -> 0.41860353 | F19: =(F18/F10)*100% -> 0.41962027 | G19: -
A20: Interest expense | B20: 610.96594 | C20: 675.92732 | D20: 925.72081 | E20: 943.80254 | F20: 981.2
A21: Nonoperating expense | B21: 1.0607048 | C21: -50.853466 | D21: -6.5913665 | E21: 59.314194 | F21: 25.3
A22: Income before income taxes | B22: 7819.5154 | C22: 6945.7359 | D22: 7183.5432 | E22: 8782.9058 | F22: =F18-F20-F21 -> 7816.1
A23: Income tax | B23: 2772.6822 | C23: 2147.4995 | D23: 2280.2989 | E23: 3463.785 | F23: 1891.8
A24: Net income | B24: =B22-B23 -> 5046.8332 | C24: =C22-C23 -> 4798.2364 | D24: =D22-D23 -> 4903.2443 | E24: =E22-E23 -> 5319.1207 | F24: =F22-F23 -> 5924.3 | G24: =(((F24/B24)^(0.2))-1)*100% -> 0.032579784
A25: Net margin | B25: =(B24/B10)*100% -> 0.17338829 | C25: =(C24/C10)*100% -> 0.17821587 | D25: =(D24/D10)*100% -> 0.19033868 | E25: =(E24/E10)*100% -> 0.22752888 | F25: =(F24/F10)*100% -> 0.2817714 | G25: -
A26: Earnings per common share (EPS)- diluted | B26: 5.11 | C26: 5.09 | D26: 5.69 | E26: 6.53 | F26: 7.54 | G26: =(((F26/B26)^(0.2))-1)*100% -> 0.08091138
A27: EPS growth | B27: - | C27: =((C26-B26)/B26)*100% -> -0.0039138943 | D27: =((D26-C26)/C26)*100% -> 0.11787819 | E27: =((E26-D26)/D26)*100% -> 0.14762742 | F27: =((F26-E26)/E26)*100% -> 0.15467075
A29: Unadjusted values
A30: Metrics | B30: Years | G30: CAGR | I30: CPI Data
B31: 2014 | C31: 2015 | D31: 2016 | E31: 2017 | F31: 2018 | I31: Years | J31: CPI | K31: Multiplier
A32: Revenues | I32: 2014 | J32: 236.736 | K32: =$J$36/J32 -> 1.0607048 | L32: 1.0607048
A33: Sales by Company-operated restaurants | B33: 18169.3 | C33: 16488.3 | D33: 15295 | E33: 12718.9 | F33: 10012.7 | G33: =(((F33/B33)^(0.2))-1)*100% -> -0.11234827 | I33: 2015 | J33: 237.017 | K33: =$J$36/J33 -> 1.0594472 | L33: 1.0594472
A34: Revenues from franchised restaurants | B34: 9272 | C34: 8924.7 | D34: 9326.9 | E34: 10101.5 | F34: 11012.5 | G34: =(((F34/B34)^(0.2))-1)*100% -> 0.035005124 | I34: 2016 | J34: 240.007 | K34: =$J$36/J34 -> 1.0462487 | L34: 1.0462487
A35: Total revenues | B35: =SUM(B33:B34) -> 27441.3 | C35: =SUM(C33:C34) -> 25413 | D35: =SUM(D33:D34) -> 24621.9 | E35: =SUM(E33:E34) -> 22820.4 | F35: =SUM(F33:F34) -> 21025.2 | G35: =(((F35/B35)^(0.2))-1)*100% -> -0.051871741 | I35: 2017 | J35: 245.12 | K35: =$J$36/J35 -> 1.0244248 | L35: 1.0244248
A36: Revenue growth | B36: - | C36: =((C35-B35)/B35)*100% -> -0.073914137 | D36: =((D35-C35)/C35)*100% -> -0.031129737 | E36: =((E35-D35)/D35)*100% -> -0.073166571 | F36: =((F35-E35)/E35)*100% -> -0.078666456 | I36: 2018 | J36: 251.107 | K36: =$J$36/J36 -> 1 | L36: 1
A37: Operating costs and expenses
A38: Company operated expenses | B38: 15288 | C38: 13977 | D38: =4896.9+4134.2+3667.7 -> 12698.8 | E38: =4033.5+3528.5+2847.6 -> 10409.6 | F38: 8266 | G38: =(((F38/B38)^(0.2))-1)*100% -> -0.11572175 | I38: Refer below link for CPI Data:
A39: Franchised expenses | B39: 1697 | C39: 1647 | D39: 1718.4 | E39: 1790 | F39: 1973 | G39: =(((F39/B39)^(0.2))-1)*100% -> 0.030597414 | I39: https://www.bls.gov/regions/mid-atlantic/data/consumerpriceindexhistorical_us_table.htm
A40: Selling, general & administrative expenses | B40: 2488 | C40: 2434 | D40: 2384.5 | E40: 2231.3 | F40: 2200 | G40: =(((F40/B40)^(0.2))-1)*100% -> -0.024304143
A41: Others | B41: 19 | C41: 209 | D41: 75.7 | E41: -1163.2 | F41: -237 | G41: =(((F41/B41)^(0.2))-1)*100% -> -2.6565286
A42: Toatal operating costs and expenses | B42: =SUM(B38:B41) -> 19492 | C42: =SUM(C38:C41) -> 18267 | D42: =SUM(D38:D41) -> 16877.4 | E42: =SUM(E38:E41) -> 13267.7 | F42: =SUM(F38:F41) -> 12202 | G42: =(((F42/B42)^(0.2))-1)*100% -> -0.089426675
A43: Operating income | B43: 7949 | C43: 7146 | D43: 7744.5 | E43: 9552.7 | F43: 8823 | G43: =(((F43/B43)^(0.2))-1)*100% -> 0.02108232
A44: Operating margin | B44: =(B43/B35)*100% -> 0.28967287 | C44: =(C43/C35)*100% -> 0.28119466 | D44: =(D43/D35)*100% -> 0.31453706 | E44: =(E43/E35)*100% -> 0.41860353 | F44: =(F43/F35)*100% -> 0.41963929 | G44: -
A45: Interest expense | B45: 576 | C45: 638 | D45: 884.8 | E45: 921.3 | F45: 981
A46: Nonoperating expense | B46: 1 | C46: -48 | D46: -6.3 | E46: 57.9 | F46: 26
A47: Income before income taxes | B47: =B43-B45-B46 -> 7372 | C47: =C43-C45-C46 -> 6556 | D47: =D43-D45-D46 -> 6866 | E47: =E43-E45-E46 -> 8573.5 | F47: =F43-F45-F46 -> 7816
A48: Income tax | B48: 2614 | C48: 2027 | D48: 2179.5 | E48: 3381.2 | F48: 1892
A49: Net income | B49: =B47-B48 -> 4758 | C49: =C47-C48 -> 4529 | D49: =D47-D48 -> 4686.5 | E49: 5192.3 | F49: =F47-F48 -> 5924 | G49: =(((F49/B49)^(0.2))-1)*100% -> 0.044811929
A50: Net margin | B50: =(B49/B35)*100% -> 0.17338829 | C50: =(C49/C35)*100% -> 0.17821587 | D50: =(D49/D35)*100% -> 0.19033868 | E50: =(E49/E35)*100% -> 0.22752888 | F50: =(F49/F35)*100% -> 0.28175713 | G50: -
A51: Earnings per common share (EPS)- diluted | B51: 4.82 | C51: 4.8 | D51: 5.44 | E51: 6.37 | F51: 7.54 | G51: =(((F51/B51)^(0.2))-1)*100% -> 0.093616015
A52: EPS growth | B52: - | C52: =((C51-B51)/B51)*100% -> -0.0041493776 | D52: =((D51-C51)/C51)*100% -> 0.13333333 | E52: =((E51-D51)/D51)*100% -> 0.17095588 | F52: =((F51-E51)/E51)*100% -> 0.18367347
A54: Go to References

Sheet Balance Sheet
A1: Balance Sheet
A2: Go to Home
A3: In millions, except share data, (10-K)
A4: All values in 2018 USD (BLS CPI-U Adjusted)
A5: Metrics | B5: Years | H5: Metrics | I5: Year
B6: 2014 | C6: 2015 | D6: 2016 | E6: 2017 | F6: 2018 | I6: 2014 | J6: 2015 | K6: 2016 | L6: 2017 | M6: 2018 | N6: 1
A7: ASSETS | H7: Return on Assets (ROA) | I7: =B56 -> 0.13897275 | J7: =C56 -> 0.1194272 | K7: =D56 -> 0.15109687 | L7: =E56 -> 0.15366525 | M7: =F56 -> 0.18055725 | N7: 1.024
A8: Current assests | H8: Debt to Asset ratio (D/A) | I8: 0.49672485 | J8: 0.69048491 | K8: 0.90068625 | L8: 0.90791245 | M8: 0.98050666 | N8: 1.046
A9: Cash and equivalents | B9: 2204.6519 | C9: 8138.9445 | D9: 1279.6764 | E9: 2522.9312 | F9: 866 | H9: Current Ratio | I9: 1.5231631 | J9: 3.2683704 | K9: 1.397976 | L9: 1.8429392 | M9: 1.3631074 | N9: 1.059
A10: Accounts and notes receivable | B10: 1288.4784 | C10: 1375.3233 | D10: 1541.9086 | E10: 2023.6288 | F10: 2441.5 | N10: 1.061
A11: Inventories | B11: 116.71 | C11: 106.0059 | D11: 61.6094 | E11: 60.2112 | F11: 51.1
A12: Prepaid expenses and other current assets | B12: 830.9752 | C12: 591.6633 | D12: 591.1992 | E12: 848.2816 | F12: 694.6
A13: Assets held for sale | B13: - | C13: - | D13: 1597.242 | E13: -
A14: Total current assets | B14: =SUM(B9:B13) -> 4440.8155 | C14: =SUM(C9:C13) -> 10211.937 | D14: =SUM(D9:D13) -> 5071.6356 | E14: =SUM(E9:E13) -> 5455.0528 | F14: =SUM(F9:F13) -> 4053.2
A16: Other assets
A17: Investments in and advances to affiliates | B17: 1065.7745 | C17: 839.4693 | D17: 759.2914 | E17: 1111.7568 | F17: 1202.8
A18: Goodwill | B18: 2902.1533 | C18: 2664.7617 | D18: 2443.979 | E18: 2436.8128 | F18: 2331.5
A19: Miscellaneous | B19: 1851.0206 | C19: 1979.3769 | D19: 1940.6438 | E19: 2624.3072 | F19: 2381
A20: Total other assets | B20: =SUM(B17:B19) -> 5818.9484 | C20: =SUM(C17:C19) -> 5483.6079 | D20: =SUM(D17:D19) -> 5143.9142 | E20: =SUM(E17:E19) -> 6172.8768 | F20: =SUM(F17:F19) -> 5915.3
A22: Property and equipments
A23: Property and equipments, at cost | B23: 41512.792 | C23: 39916.252 | D23: 36027.796 | E23: 37505.434 | F23: 37193.6
A24: Accumulated depreciation and amortization | B24: -15457.285 | C24: -15434.713 | D24: -13792.347 | E24: -14518.374 | F24: -14350.9
A25: Net | B25: 26055.507 | C25: 24481.538 | D25: 22235.45 | E25: =SUM(E23:E24) -> 22987.059 | F25: =SUM(F23:F24) -> 22842.7
A27: Total assets | B27: =SUM(B25,B20,B14) -> 36315.271 | C27: =SUM(C25,C20,C14) -> 40177.083 | D27: =SUM(D25,D20,D14) -> 32450.999 | E27: =SUM(E25,E20,E14) -> 34614.989 | F27: =SUM(F25,F20,F14) -> 32811.2
A29: LIABILITIES AND SHAREHOLDER'S EQUITY
A30: Current liabilities
A31: Accounts payable | B31: 912.5661 | C31: 926.3073 | D31: 790.776 | E31: 946.9952 | F31: 1207.9
A32: Income taxes | B32: 176.9748 | C32: 163.9332 | D32: 279.4912 | E32: 272.1792 | F32: 228.3
A33: Other taxes | B33: 350.13 | C33: 327.231 | D33: 278.5498 | E33: 282.0096 | F33: 253.7
A34: Accrued interest | B34: 247.9557 | C34: 246.8529 | D34: 258.885 | E34: 285.0816 | F34: 297
A35: Accrued payroll and other liabilities | B35: 1227.8953 | C35: 1460.1492 | D35: 1212.6278 | E35: 1173.7088 | F35: 986.6
A36: Current maturities | B36: - | C36: - | D36: 80.7512 | E36: - | F36: -
A37: Liabilities held for sale | B37: - | C37: - | D37: 726.7608 | E37: - | F37: -
A38: Total current liabilities | B38: =SUM(B31:B37) -> 2915.5219 | C38: =SUM(C31:C37) -> 3124.4736 | D38: =SUM(D31:D37) -> 3627.8418 | E38: =SUM(E31:E37) -> 2959.9744 | F38: =SUM(F31:F37) -> 2973.5
A40: Long-term debt | B40: 15846.778 | C40: 25545.304 | D40: 27068.911 | E40: 30245.274 | F40: 31075.3
A41: Long-term income taxes | B41: - | C41: - | D41: - | E41: 2427.8016 | F41: 2081.2
A42: Deferred revenues | B42: - | C42: - | D42: - | E42: - | F42: 627.8
A43: Other long-term liabilities | B43: 2191.9199 | C43: 2196.366 | D43: 2159.2578 | E43: 1182.1056 | F43: 1096.3
A44: Deferred income taxes | B44: 1723.5945 | C44: 1804.8537 | D44: 1900.6866 | E44: 1146.2656 | F44: 1215.5
A45: Total Debt | B45: =B40+B43 -> 18038.698 | C45: =C40+C43 -> 27741.67 | D45: =D40+D43 -> 29228.169 | E45: =E40+E43 -> 31427.379 | F45: =F40+F43 -> 32171.6
A46: Shareholder's equity (deficit)
A47: Preferred stock | B47: - | C47: - | D47: - | E47: - | F47: -
A48: Common stock | B48: 16.6 | C48: 16.6 | D48: 16.6 | E48: 16.6 | F48: 16.6
A49: Additional paid-in capital | B49: 6619.6851 | C49: 6918.8706 | D49: 7068.7634 | E49: 7242.1376 | F49: 7376
A50: Retained earnings | B50: 45935.464 | C50: 47225.575 | D50: 48348.944 | E50: 49485.619 | F50: 50487
A51: Acuumulated other comprehensive income | B51: -1612.4017 | C51: -3049.7082 | D51: -3235.1734 | E51: -2230.6816 | F51: -2609.5
A52: Common stock in treasury | B52: -37322.903 | C52: -43606.231 | D52: -54505.596 | E52: -57860.506 | F52: -61528.5
A53: Total shareholder's equity (deficit) | B53: =SUM(B48:B52) -> 13636.445 | C53: =SUM(C48:C52) -> 7505.1067 | D53: =SUM(D48:D52) -> -2306.4614 | E53: =SUM(E48:E52) -> -3346.8304 | F53: =SUM(F48:F52) -> -6258.4
A55: Net income | B55: 5046.8332 | C55: 4798.2364 | D55: 4903.2443 | E55: 5319.1207 | F55: 5924.3
A56: Return on Assets (ROA) | B56: =(B55/B27) -> 0.13897275 | C56: =(C55/C27) -> 0.1194272 | D56: =(D55/D27) -> 0.15109687 | E56: =(E55/E27) -> 0.15366525 | F56: =(F55/F27) -> 0.18055725
A57: Debt to Asset ratio (D/A) | B57: =(B40+B43)/B27 -> 0.49672485 | C57: =(C40+C43)/C27 -> 0.69048491 | D57: =(D40+D43)/D27 -> 0.90068625 | E57: =(E40+E43)/E27 -> 0.90791245 | F57: =(F40+F43)/F27 -> 0.98050666
A58: Current Ratio | B58: =(B14/B38) -> 1.5231631 | C58: =(C14/C38) -> 3.2683704 | D58: =(D14/D38) -> 1.397976 | E58: =(E14/E38) -> 1.8429392 | F58: =(F14/F38) -> 1.3631074
A60: Total liabilities and shareholder's equity (deficit) | B60: =SUM(B53,B40:B44,B38) -> 36314.259 | C60: =SUM(C53,C40:C44,C38) -> 40176.104 | D60: =SUM(D53,D40:D44,D38) -> 32450.236 | E60: =SUM(E53,E40:E44,E38) -> 34614.59 | F60: =SUM(F53,F40:F44,F38) -> 32811.2
A63: CPI Adjustment Note: Monetary values have been CPI-adjusted to reflect real purchasing power, while common stock remains unadjusted as it represents share count, not monetary value. This may cause a minor variance in the balance sheet equation due to mixed adjustment methodologies.
A66: Unadjusted values
A67: Metrics | B67: Years
B68: 2014 | C68: 2015 | D68: 2016 | E68: 2017 | F68: 2018
A69: ASSETS
A70: Current assests
A71: Cash and equivalents | B71: 2077.9 | C71: 7685.5 | D71: 1223.4 | E71: 2463.8 | F71: 866
A72: Accounts and notes receivable | B72: 1214.4 | C72: 1298.7 | D72: 1474.1 | E72: 1976.2 | F72: 2441.5
A73: Inventories | B73: 110 | C73: 100.1 | D73: 58.9 | E73: 58.8 | F73: 51.1
A74: Prepaid expenses and other current assets | B74: 783.2 | C74: 558.7 | D74: 565.2 | E74: 828.4 | F74: 694.6
A75: Assets held for sale | B75: - | C75: - | D75: 1527 | E75: -
A76: Total current assets | B76: =SUM(B71:B75) -> 4185.5 | C76: =SUM(C71:C75) -> 9643 | D76: =SUM(D71:D75) -> 4848.6 | E76: =SUM(E71:E75) -> 5327.2 | F76: =SUM(F71:F75) -> 4053.2
A78: Other assets
A79: Investments in and advances to affiliates | B79: 1004.5 | C79: 792.7 | D79: 725.9 | E79: 1085.7 | F79: 1202.8
A80: Goodwill | B80: 2735.3 | C80: 2516.3 | D80: 2336.5 | E80: 2379.7 | F80: 2331.5
A81: Miscellaneous | B81: 1744.6 | C81: 1869.1 | D81: 1855.3 | E81: 2562.8 | F81: 2381
A82: Total other assets | B82: =SUM(B79:B81) -> 5484.4 | C82: =SUM(C79:C81) -> 5178.1 | D82: =SUM(D79:D81) -> 4917.7 | E82: =SUM(E79:E81) -> 6028.2 | F82: =SUM(F79:F81) -> 5915.3
A84: Property and equipments
A85: Property and equipments, at cost | B85: 39126.1 | C85: 37692.4 | D85: 34443.4 | E85: 36626.4 | F85: 37193.6
A86: Accumulated depreciation and amortization | B86: -14568.6 | C86: -14574.8 | D86: -13185.8 | E86: -14178.1 | F86: -14350.9
A87: Net | B87: =SUM(B85:B86) -> 24557.5 | C87: =SUM(C85:C86) -> 23117.6 | D87: =SUM(D85:D86) -> 21257.6 | E87: =SUM(E85:E86) -> 22448.3 | F87: =SUM(F85:F86) -> 22842.7
A89: Total assets | B89: =SUM(B87,B82,B76) -> 34227.4 | C89: =SUM(C87,C82,C76) -> 37938.7 | D89: =SUM(D87,D82,D76) -> 31023.9 | E89: =SUM(E87,E82,E76) -> 33803.7 | F89: =SUM(F87,F82,F76) -> 32811.2
A91: LIABILITIES AND SHAREHOLDER'S EQUITY
A92: Current liabilities
A93: Accounts payable | B93: 860.1 | C93: 874.7 | D93: 756 | E93: 924.8 | F93: 1207.9
A94: Income taxes | B94: 166.8 | C94: 154.8 | D94: 267.2 | E94: 265.8 | F94: 228.3
A95: Other taxes | B95: 330 | C95: 309 | D95: 266.3 | E95: 275.4 | F95: 253.7
A96: Accrued interest | B96: 233.7 | C96: 233.1 | D96: 247.5 | E96: 278.4 | F96: 297
A97: Accrued payroll and other liabilities | B97: 1157.3 | C97: 1378.8 | D97: 1159.3 | E97: 1146.2 | F97: 986.6
A98: Current maturities | B98: - | C98: - | D98: 77.2 | E98: - | F98: -
A99: Liabilities held for sale | B99: - | C99: - | D99: 694.8 | E99: - | F99: -
A100: Total current liabilities | B100: =SUM(B93:B99) -> 2747.9 | C100: =SUM(C93:C99) -> 2950.4 | D100: =SUM(D93:D99) -> 3468.3 | E100: =SUM(E93:E99) -> 2890.6 | F100: =SUM(F93:F99) -> 2973.5
A102: Long-term debt | B102: 14935.7 | C102: 24122.1 | D102: 25878.5 | E102: 29536.4 | F102: 31075.3
A103: Long-term income taxes | B103: - | C103: - | D103: - | E103: 2370.9 | F103: 2081.2
A104: Deferred revenues | B104: - | C104: - | D104: - | E104: - | F104: 627.8
A105: Other long-term liabilities | B105: 2065.9 | C105: 2074 | D105: 2064.3 | E105: 1154.4 | F105: 1096.3
A106: Deferred income taxes | B106: 1624.5 | C106: 1704.3 | D106: 1817.1 | E106: 1119.4 | F106: 1215.5
A107: Total Debt | B107: =SUM(B102,B105) -> 17001.6 | C107: =SUM(C102,C105) -> 26196.1 | D107: =SUM(D102,D105) -> 27942.8 | E107: =SUM(E102,E105) -> 30690.8 | F107: =F102+F105 -> 32171.6
A108: Shareholder's equity (deficit)
A109: Preferred stock | B109: - | C109: - | D109: - | E109: - | F109: -
A110: Common stock | B110: 16.6 | C110: 16.6 | D110: 16.6 | E110: 16.6 | F110: 16.6
A111: Additional paid-in capital | B111: 6239.1 | C111: 6533.4 | D111: 6757.9 | E111: 7072.4 | F111: 7376
A112: Retained earnings | B112: 43294.5 | C112: 44594.5 | D112: 46222.7 | E112: 48325.8 | F112: 50487
A113: Acuumulated other comprehensive income | B113: -1519.7 | C113: -2879.8 | D113: -3092.9 | E113: -2178.4 | F113: -2609.5
A114: Common stock in treasury | B114: -35177.1 | C114: -41176.8 | D114: -52108.6 | E114: -56504.4 | F114: -61528.5
A115: Total shareholder's equity (deficit) | B115: =SUM(B110:B114) -> 12853.4 | C115: =SUM(C110:C114) -> 7087.9 | D115: =SUM(D110:D114) -> -2204.3 | E115: =SUM(E110:E114) -> -3268 | F115: =SUM(F110:F114) -> -6258.4
A116: Total liabilities and shareholder's equity (deficit) | B116: =SUM(B115,B100,B102:B106) -> 34227.4 | C116: =SUM(C115,C100,C102:C106) -> 37938.7 | D116: =SUM(D115,D100,D102:D106) -> 31023.9 | E116: =SUM(E115,E100,E102:E106) -> 33803.7 | F116: =SUM(F115,F100,F102:F106) -> 32811.2
...

Sheet CF Statement
A1: Cash Flow Statement
A2: Go to Home
A3: In millions, (10-K)
A4: All values in 2018 USD (BLS CPI-U Adjusted)
A5: Metrics | B5: Years | H5: Key Ratios | I5: Years
B6: 2014 | C6: 2015 | D6: 2016 | E6: 2017 | F6: 2018 | J6: 2014 | K6: 2015 | L6: 2016 | M6: 2017 | N6: 2018
A7: Operating Activities | H7: Cash Flow Performance | I7: Operating Cash Flow OCF Margin
A8: Net income | B8: 5048.238 | C8: 4796.211 | D8: 4902.079 | E8: 5316.9152 | F8: 5924.3 | I8: OCF/Revenue | J8: =B21/B50 -> 0.24533726 | K8: =C21/C50 -> 0.25719277 | L8: =D21/D50 -> 0.24604762 | M8: =E21/E50 -> 0.24315517 | N8: =F21/F50 -> 0.33135
A9: Charges and credits
A10: Depreciation and amortization | B10: 1744.8145 | C10: 1647.4863 | D10: 1586.259 | E10: 1396.1216 | F10: 1482 | I10: Free Cash Flow FCF
A11: Deferred income taxes | B11: -96.2327 | C11: -1.4826 | D11: -563.3756 | E11: -37.2736 | F11: 102.6 | I11: OCF-CapEx | J11: =B21+B24 -> 4400.0731 | K11: =C21+C24 -> 5003.6691 | L11: =D21+D24 -> 4433.471 | M11: =E21+E24 -> 3786.24 | N11: =F21+F24 -> 4225
A12: Share-based compensation | B12: 119.6808 | C12: 116.49 | D12: 137.3398 | E12: 120.32 | F12: 125.1 | H12: Liquidity and Solvency | I12: Cash Flow to Debt ratio
A13: Net gain on sale of businesses | B13: - | C13: - | D13: -324.9922 | E13: -1183.5392 | F13: -308.8 | I13: OCF/Total debt | J13: =B21/B51 -> 0.39587451 | K13: =C21/C51 -> 0.24960967 | L13: =D21/D51 -> 0.21685729 | M13: =E21/E51 -> 0.18087505 | N13: =F21/F51 -> 0.21654814
A14: Other | B14: 392.0395 | C14: 188.0784 | D14: 426.3496 | E14: 1075.9168 | F14: 114.2
A15: Changes in working capital | I15: Cash Flow Coverage ratio
A16: Accounts receivable | B16: 28.647 | C16: -191.2554 | D16: -166.314 | E16: -348.8768 | F16: -479.4 | I16: OCF/ Interest paid | J16: =B21/B47 -> 11.741975 | K16: =C21/C47 -> 10.20412 | L16: =D21/D47 -> 6.9371494 | M16: =E21/E47 -> 6.2711252 | N16: =F21/F47 -> 7.2600042
A17: Inventories, prepaid expenses and other current assets | B17: -5.1989 | C17: 47.5491 | D17: 29.3926 | E17: -38.1952 | F17: -1.9
A18: Accounts payable | B18: -79.2567 | C18: -15.885 | D18: 93.9308 | E18: -61.1328 | F18: 129.4 | I18: Capex to OCF ratio
A19: Income taxes | B19: 3.5013 | C19: -68.1996 | D19: 177.5062 | E19: -405.9136 | F19: -33.4 | I19: Capex/OCF | J19: =B24/B21 -> -0.38383478 | K19: =C24/C21 -> -0.27740564 | L19: =D24/D21 -> -0.30053139 | M19: =E24/E21 -> -0.3339278 | N19: =F24/F21 -> -0.39354357
A20: Other accrued liabilities | B20: -15.1723 | C20: 405.597 | D20: 40.1664 | E20: -149.9136 | F20: -87.4 | H20: Quality of earnings | I20: Quality of earning ratio
A21: Total cash by Operations (OCF) | B21: =SUM(B8:B20) -> 7141.0605 | C21: =SUM(C8:C20) -> 6924.5892 | D21: =SUM(D8:D20) -> 6338.3416 | E21: =SUM(E8:E20) -> 5684.4288 | F21: =SUM(F8:F20) -> 6966.7 | I21: OCF/Net Income | J21: =B21/B52 -> 1.2053847 | K21: =C21/C52 -> 1.1688451 | L21: =D21/D52 -> 1.0698887 | M21: =E21/E52 -> 0.95951063 | N21: =F21/F52 -> 1.1759533
H22: Return Ratios | I22: Cash Return on Equity (CROA)
A23: Investing Activities | I23: OCF/Total assets | J23: =B21/B53 -> 0.1966407 | K23: =C21/C53 -> 0.17235171 | L23: =D21/D53 -> 0.19532038 | M23: =E21/E53 -> 0.16421871 | N23: =F21/F53 -> 0.21232689
A24: Capital expenditures (CapEx) | B24: -2740.9874 | C24: -1920.9201 | D24: -1904.8706 | E24: -1898.1888 | F24: -2741.7
A25: Purchases of restaurant businesses | B25: -180.9005 | C25: -148.8954 | D25: -114.537 | E25: -78.848 | F25: -101.7 | I25: Cash Return on Equity (CROE)
A26: Sales of restaurant businesses | B26: 519.7839 | C26: 586.8978 | D26: 1020.4776 | E26: 998.1952 | F26: 530.8 | I26: OCF/Shareholder's equity | J26: =B21/B54 -> 0.52367465 | K26: =C21/C54 -> 0.92265033 | L26: =D21/D54 -> -2.7480805 | M26: =E21/E54 -> -1.6984514 | N26: =F21/F54 -> -1.1131759
A27: Proceeds from sale (China and Hong Kong) | B27: - | C27: - | D27: - | E27: 1635.328 | F27: - | H27: Dividend and Sustainability | I27: Sustained Cash Flow Index
A28: Sales of property | B28: - | C28: - | D28: 86.7134 | E28: 170.8032 | F28: 160.4 | I28: (OCF-Dividends)/Net income | J28: =(B21+B37)/B52 -> 0.62940405 | K28: =(C21+C37)/C52 -> 0.5914119 | L28: =(D21+D37)/D52 -> 0.52993002 | M28: =(E21+E37)/E52 -> 0.42555036 | N28: =(F21+F37)/F52 -> 0.62636936
A29: Other | B29: -43.3949 | C29: -20.8623 | D29: -114.537 | E29: -251.8016 | F29: -302.9
A30: Total cash by investing activities | B30: =SUM(B24:B29) -> -2445.4989 | C30: =SUM(C24:C29) -> -1503.78 | D30: =SUM(D24:D29) -> -1026.7536 | E30: =SUM(E24:E29) -> 575.488 | F30: =SUM(F24:F29) -> -2455.1 | I30: Dividend Coverage Ratio
I31: OCF/Dividends paid | J31: =B21/(-(B37)) -> 2.0927521 | K31: =C21/(-(C37)) -> 2.0242083 | L31: =D21/(-(D37)) -> 1.981427 | M31: =E21/(-(E37)) -> 1.7969701 | N31: =F21/(-(F37)) -> 2.1397156
A32: Financing activities (used for) | I32: Net income/Dividends paid | J32: =B52/(-(B37)) -> 1.7361695 | K32: =C52/(-(C37)) -> 1.731802 | L32: =D52/(-(D37)) -> 1.8519936 | M32: =E52/(-(E37)) -> 1.8727985 | N32: =F52/(-(F37)) -> 1.8195583
A33: Net short-term borrowings | B33: 541.5344 | C33: 624.4923 | D33: -299.3652 | E33: -1075.5072 | F33: 95.9 | H33: Market performance | I33: Cash Flow Yield
A34: Long-term financing isssuances | B34: 1634.5766 | C34: 10822.98 | D34: 3953.357 | E34: 4840.96 | F34: 3794.5 | I34: OCF/Market cap | J34: =B21/B55 -> 0.078309689 | K34: =C21/C55 -> 0.063832865 | L34: =D21/D55 -> 0.062706189 | M34: =E21/E55 -> 0.041428677 | N34: =F21/F55 -> 0.050892688
A35: Long-term financing repayments | B35: -581.5341 | C35: -1116.7155 | D35: -860.7534 | E35: -1688.9856 | F35: -1759.6
A36: Treasury stock purchases | B36: -3393.7146 | C36: -6459.0528 | D36: -11684.866 | E36: -4798.1568 | F36: -5207.7
A37: Common stock dividends | B37: -3412.2821 | C37: -3420.8877 | D37: -3198.8772 | E37: -3163.3408 | F37: -3255.9 | J37: 1.061
A38: Proceeds from stock option exercises | B38: 249.7594 | C38: 335.9148 | D38: 313.1724 | E38: 467.7632 | F38: 403.2 | J38: 1.059
A39: Excess tax benefit on share-based compensation | B39: 75.2249 | C39: 54.1149 | D39: - | E39: - | F39: - | J39: 1.046
A40: Other | B40: -13.5808 | C40: -62.1633 | D40: -3.138 | E40: -20.992 | F40: -20 | J40: 1.024
A41: Total by Financing activities | B41: =SUM(B33:B40) -> -4900.0163 | C41: =SUM(C33:C40) -> 778.6827 | D41: =SUM(D33:D40) -> -11780.47 | E41: =SUM(E33:E40) -> -5438.2592 | F41: =SUM(F33:F40) -> -5949.6 | J41: 1
A42: Effect of exchange rates on cash | B42: -560.1019 | C42: -261.3612 | D42: -108.4702 | E42: 270.336 | F42: -159.8
A43: Cash and equivalents increase | B43: -764.7688 | C43: 5938.4484 | D43: -6577.3526 | E43: 1091.9936 | F43: -1597.8
A44: Cash in cash balances of business for sale | B44: - | C44: - | D44: -182.004 | E44: 178.176 | F44: -
A45: Cash and equivalents at beginning of year | B45: 2969.4207 | C45: 2200.4961 | D45: 8039.033 | E45: 1252.7616 | F45: 2463.8
A46: Cash and equivalents at end of year | B46: =SUM(B43:B45) -> 2204.6519 | C46: =SUM(C43:C45) -> 8138.9445 | D46: =SUM(D43:D45) -> 1279.6764 | E46: =SUM(E43:E45) -> 2522.9312 | F46: =SUM(F43:F45) -> 866
A47: Interest paid | B47: 608.1652 | C47: 678.6072 | D47: 913.681 | E47: 906.4448 | F47: 959.6
A48: Income tax paid | B48: 2533.9863 | C48: 2102.5386 | D48: 2497.325 | E48: 2853.1712 | F48: 1734.4
A49: Required values from Income sheet and Balance sheet:
A50: Total revenues | B50: 29107.117 | C50: 26923.732 | D50: 25760.63 | E50: 23377.783 | F50: 21025.2
A51: Total Debt | B51: 18038.698 | C51: 27741.67 | D51: 29228.169 | E51: 31427.379 | F51: 32171.6
A52: Net income | B52: 5924.3 | C52: 5924.3 | D52: 5924.3 | E52: 5924.3 | F52: 5924.3
A53: Total assets | B53: 36315.271 | C53: 40177.083 | D53: 32450.999 | E53: 34614.989 | F53: 32811.2
A54: Total shareholder's equity (deficit) | B54: 13636.445 | C54: 7505.1067 | D54: -2306.4614 | E54: -3346.8304 | F54: -6258.4
A55: Market Capital (use below link for Market Cap data) | B55: 91190 | C55: 108,480.0 | D55: 101,080.0 | E55: 137,210.0 | F55: 136,890.0
A56: https://stockanalysis.com/stocks/mcd/market-cap/
A59: Unadjusted values
A60: Metrics | B60: Years
B61: 2014 | C61: 2015 | D61: 2016 | E61: 2017 | F61: 2018
A62: Operating Activities
A63: Net income | B63: 4757.8 | C63: 4529.3 | D63: 4686.5 | E63: 5192.3 | F63: 5924.3
A64: Charges and credits
A65: Depreciation and amortization | B65: 1644.5 | C65: 1555.7 | D65: 1516.5 | E65: 1363.4 | F65: 1482
A66: Deferred income taxes | B66: -90.7 | C66: -1.4 | D66: -538.6 | E66: -36.4 | F66: 102.6
A67: Share-based compensation | B67: 112.8 | C67: 110 | D67: 131.3 | E67: 117.5 | F67: 125.1
A68: Net gain on sale of businesses | B68: - | C68: - | D68: -310.7 | E68: -1155.8 | F68: -308.8
A69: Other | B69: 369.5 | C69: 177.6 | D69: 407.6 | E69: 1050.7 | F69: 114.2
A70: Changes in working capital
A71: Accounts receivable | B71: 27 | C71: -180.6 | D71: -159 | E71: -340.7 | F71: -479.4
A72: Inventories, prepaid expenses and other current assets | B72: -4.9 | C72: 44.9 | D72: 28.1 | E72: -37.3 | F72: -1.9
A73: Accounts payable | B73: -74.7 | C73: -15 | D73: 89.8 | E73: -59.7 | F73: 129.4
A74: Income taxes | B74: 3.3 | C74: -64.4 | D74: 169.7 | E74: -396.4 | F74: -33.4
A75: Other accrued liabilities | B75: -14.3 | C75: 383 | D75: 38.4 | E75: -146.4 | F75: -87.4
A76: Total cash by Operations (OCF) | B76: =SUM(B63:B75) -> 6730.3 | C76: =SUM(C63:C75) -> 6539.1 | D76: =SUM(D63:D75) -> 6059.6 | E76: =SUM(E63:E75) -> 5551.2 | F76: =SUM(F63:F75) -> 6966.7
A78: Investing Activities
A79: Capital expenditures (CapEx) | B79: -2583.4 | C79: -1813.9 | D79: -1821.1 | E79: -1853.7 | F79: -2741.7
A80: Purchases of restaurant businesses | B80: -170.5 | C80: -140.6 | D80: -109.5 | E80: -77 | F80: -101.7
A81: Sales of restaurant businesses | B81: 489.9 | C81: 554.2 | D81: 975.6 | E81: 974.8 | F81: 530.8
A82: Proceeds from sale (China and Hong Kong) | B82: - | C82: - | D82: - | E82: 1597 | F82: -
A83: Sales of property | B83: - | C83: - | D83: 82.9 | E83: 166.8 | F83: 160.4
A84: Other | B84: -40.9 | C84: -19.7 | D84: -109.5 | E84: -245.9 | F84: -302.9
A85: Total cash by investing activities | B85: =SUM(B79:B84) -> -2304.9 | C85: =SUM(C79:C84) -> -1420 | D85: =SUM(D79:D84) -> -981.6 | E85: =SUM(E79:E84) -> 562 | F85: =SUM(F79:F84) -> -2455.1
A87: Financing activities (used for)
A88: Net short-term borrowings | B88: 510.4 | C88: 589.7 | D88: -286.2 | E88: -1050.3 | F88: 95.9
A89: Long-term financing isssuances | B89: 1540.6 | C89: 10220 | D89: 3779.5 | E89: 4727.5 | F89: 3794.5
A90: Long-term financing repayments | B90: -548.1 | C90: -1054.5 | D90: -822.9 | E90: -1649.4 | F90: -1759.6
A91: Treasury stock purchases | B91: -3198.6 | C91: -6099.2 | D91: -11171 | E91: -4685.7 | F91: -5207.7
A92: Common stock dividends | B92: -3216.1 | C92: -3230.3 | D92: -3058.2 | E92: -3089.2 | F92: -3255.9
A93: Proceeds from stock option exercises | B93: 235.4 | C93: 317.2 | D93: 299.4 | E93: 456.8 | F93: 403.2
A94: Excess tax benefit on share-based compensation | B94: 70.9 | C94: 51.1 | D94: - | E94: - | F94: -
A95: Other | B95: -12.8 | C95: -58.7 | D95: -3 | E95: -20.5 | F95: -20
A96: Total cash provided by (used for) Financing activities | B96: =SUM(B88:B95) -> -4618.3 | C96: =SUM(C88:C95) -> 735.3 | D96: =SUM(D88:D95) -> -11262.4 | E96: =SUM(E88:E95) -> -5310.8 | F96: =SUM(F88:F95) -> -5949.6
A97: Effect of exchange rates on cash | B97: -527.9 | C97: -246.8 | D97: -103.7 | E97: 264 | F97: -159.8
A98: Cash and equivalents increase | B98: -720.8 | C98: 5607.6 | D98: -6288.1 | E98: 1066.44 | F98: -1597.8
A99: Cash in cash balances of business for sale | B99: - | C99: - | D99: -174 | E99: 174 | F99: -
A100: Cash and equivalents at beginning of year | B100: 2798.7 | C100: 2077.9 | D100: 7685.5 | E100: 1223.4 | F100: 2463.8
A101: Cash and equivalents at end of year | B101: 2077.9 | C101: =SUM(C98:C100) -> 7685.5 | D101: =SUM(D98:D100) -> 1223.4 | E101: =SUM(E98:E100) -> 2463.84 | F101: =SUM(F98:F100) -> 866
A102: Interest paid | B102: 573.2 | C102: 640.8 | D102: 873.5 | E102: 885.2 | F102: 959.6
A103: Income tax paid | B103: 2388.3 | C103: 1985.4 | D103: 2387.5 | E103: 2786.3 | F103: 1734.4
A105: Go to References

Sheet Ratios
A1: Ratios
A2: Go to Home
A4: Key Ratios from Income Statement: | C4: Go to Overview | I4: Key Ratios from Balance Sheet: | K4: Go to Balance Sheet | P4: Key ratios from Cash Flow Statement: | S4: Go to CF Statement
B5: Metrics | C5: Years | J5: Metrics | K5: Year | R5: Years: | S5: 2014 | T5: 2015 | U5: 2016 | V5: 2017 | W5: 2018
C6: 2014 | D6: 2015 | E6: 2016 | F6: 2017 | G6: 2018 | K6: 2014 | L6: 2015 | M6: 2016 | N6: 2017 | O6: 2018 | Q6: Cash Flow Performance | R6: Operating Cash Flow OCF Margin
B7: Revenue growth | C7: - | D7: -0.075012075 | E7: -0.043199893 | F7: -0.092499548 | G7: -0.10063328 | J7: Return on Assets (ROA) | K7: 0.16313523 | L7: 0.14745471 | M7: 0.1825614 | N7: 0.1711484 | O7: 0.18054811 | R7: OCF/Revenue | S7: 0.24533726 | T7: 0.25719277 | U7: 0.24604762 | V7: 0.24315517 | W7: 0.33135
B8: EPS growth | C8: - | D8: -0.0058708415 | E8: 0.12007874 | F8: 0.14586995 | G8: 0.15644172 | J8: Debt to Asset ratio (D/A) | K8: 0.49672485 | L8: 0.69048491 | M8: 0.90068625 | N8: 0.90791245 | O8: 0.98050666
B9: Operating margin | C9: 0.28967603 | D9: 0.28119466 | E9: 0.31453706 | F9: 0.41862401 | G9: 0.41964328 | J9: Current Ratio | K9: 1.5231631 | L9: 3.2683704 | M9: 1.397976 | N9: 1.8429392 | O9: 1.3631074 | R9: Free Cash Flow FCF
B10: Net margin | C10: 0.17339018 | D10: 0.17821587 | E10: 0.1903176 | F10: 0.22751972 | G10: 0.28175981 | R10: OCF-CapEx | S10: 4588.9311 | T10: 5003.6691 | U10: 4433.471 | V10: 3786.24 | W10: 4225
A28: Revenue Growth: | I28: Return on Assets (ROA): | P28: Operating Cash Flow OCF Margin:
A29: Revenue growth represents the percentage increase or decrease in a company's total revenue compared to the previous year. It indicates the company's ability to expand sales and generate higher income over time. | I29: ROA measures a company's profitability relative to its total assets. It indicates how efficiently the company utilizes its assets to generate net income. | P29: OCF margin measures how much of a company’s revenue is converted into operating cash flow. A higher margin indicates strong cash-generating efficiency.
A33: EPS Growth: | I33: Debt to Asset Ratio (D/A): | P33: Free Cash Flow FCF:
A34: Earnings Per Share (EPS) growth measures the rate at which a company's net earnings per share increase or decrease over time. A positive trend suggests improving profitability and potential value for investors. | I34: The debt-to-asset ratio measures the proportion of a company's assets financed by debt. A higher ratio suggests greater financial leverage and potential risk. | P34: FCF represents the cash a company generates after accounting for capital expenditures (CapEx). It indicates the company’s ability to reinvest, pay dividends, or reduce debt.
A38: Operating Margin: | I38: Current Ratio:
A39: Operating margin shows the proportion of revenue that remains after covering all operating expenses, excluding interest and taxes. It reflects the company’s efficiency in managing operational costs. | I39: The current ratio assesses a company's ability to cover short-term liabilities with its short-term assets. A ratio above 1 indicates strong liquidity.
A43: Net Margin:
A44: Net margin represents the percentage of revenue that remains as profit after all expenses, including taxes and interest, are deducted. A higher net margin indicates stronger profitability.
A49: Key ratios from Cash Flow Statement: | C49: Go to CF Statement | I49: Key ratios from Cash Flow Statement: | K49: Go to CF Statement | P49: Key ratios from Cash Flow Statement: | S49: Go to CF Statement
B50: Years: | C50: 2014 | D50: 2015 | E50: 2016 | F50: 2017 | G50: 2018
A51: Liquidity and Solvency | B51: Cash Flow to Debt ratio | J51: Years: | K51: 2014 | L51: 2015 | M51: 2016 | N51: 2017 | O51: 2018 | R51: Years: | S51: 2014 | T51: 2015 | U51: 2016 | V51: 2017 | W51: 2018
B52: OCF/Total debt | C52: 0.40634411 | D52: 0.24960967 | E52: 0.21685729 | F52: 0.18087505 | G52: 0.21654814 | I52: Quality of earnings | J52: Quality of earning ratio | Q52: Return Ratios | R52: Cash Return on Equity (CROA)
J53: OCF/Net Income | K53: 1.2372632 | L53: 1.1688451 | M53: 1.0698887 | N53: 0.95951063 | O53: 1.1759533 | R53: OCF/Total assets | S53: 0.20184121 | T53: 0.17235171 | U53: 0.19532038 | V53: 0.16421871 | W53: 0.21232689
B54: Cash Flow Coverage ratio
B55: OCF/ Interest paid | C55: 12.052512 | D55: 10.20412 | E55: 6.9371494 | F55: 6.2711252 | G55: 7.2600042 | R55: Cash Return on Equity (CROE)
R56: OCF/Shareholder's equity | S56: 0.53752416 | T56: 0.92265033 | U56: -2.7480805 | V56: -1.6984514 | W56: -1.1131759
B57: Capex to OCF ratio
B58: Capex/OCF | C58: -0.37394514 | D58: -0.27740564 | E58: -0.30053139 | F58: -0.3339278 | G58: -0.39354357
A76: Cash Flow to Debt Ratio: | I76: Quality of earning ratio: | P76: Cash Return on Equity (CROA):
A77: This ratio measures a company's ability to cover its total debt using its operating cash flow. A higher ratio indicates a stronger ability to repay debt. | I77: This ratio compares operating cash flow to net income, assessing the reliability of reported earnings. A higher ratio indicates that earnings are backed by strong cash flow rather than accounting adjustments. | P77: Measures how efficiently a company generates cash flow from its total assets. A higher CROA indicates better asset utilization in generating cash flow.
A81: Cash Flow Coverage Ratio: | P81: Cash Return on Equity (CROE):
A82: This ratio evaluates how well a company can cover its interest payments with operating cash flow. A higher value suggests better financial stability. | P82: Evaluates how much operating cash flow is generated per unit of shareholder's equity. A higher CROE suggests strong profitability and financial efficiency.
A86: Capex to OCF Ratio:
A87: This ratio shows the proportion of operating cash flow spent on capital expenditures. A lower ratio suggests more free cash flow available for other uses.
A96: Key ratios from Cash Flow Statement: | D96: Go to CF Statement | I96: Key ratios from Cash Flow Statement: | L96: Go to CF Statement
B98: Years: | C98: 2014 | D98: 2015 | E98: 2016 | F98: 2017 | G98: 2018 | J98: Years: | K98: 2014 | L98: 2015 | M98: 2016 | N98: 2017 | O98: 2018
A99: Dividend and Sustainability | B99: Sustained Cash Flow Index | I99: Market Performance | J99: Cash Flow Yield
B100: (OCF-Dividends)/Net income | C100: 0.66128258 | D100: 0.5914119 | E100: 0.52993002 | F100: 0.42555036 | G100: 0.62636936 | J100: OCF/Market cap | K100: 0.080380727 | L100: 0.063832865 | M100: 0.062706189 | N100: 0.041428677 | O100: 0.050892688
B102: Dividend Coverage Ratio
B103: OCF/Dividends paid | C103: 2.1480986 | D103: 2.0242083 | E103: 1.981427 | F103: 1.7969701 | G103: 2.1397156
B106: Net income/Dividends paid | C106: 1.7361695 | D106: 1.731802 | E106: 1.8519936 | F106: 1.8727985 | G106: 1.8195583
A125: Sustained Cash Flow Index: | I125: Cash Flow Yeild:
A126: Indicates the proportion of net income retained after paying dividends. A higher value suggests stronger cash flow sustainability. | I126: Measures the cash flow generated relative to the company's market capitalization. A higher yield suggests stronger cash-generating ability in relation to its valuation.
A130: Dividend Coverage Ratio:
A131: OCF/ Dividend paid:
A132: Measures the ability of a company to cover its dividend payments with its operating cash flow. A higher ratio indicates better dividend-paying capacity.
A135: Net Income/ Dividends paid:
A136: Shows how much of the company's net income is used to pay dividends. A lower ratio may indicate higher dividend payouts relative to earnings.

Sheet Segment Analysis
A1: Segment Analysis
A2: Go to Home
A3: In millions, (10-K)
A4: All values in 2018 USD (BLS CPI-U Adjusted)
A5: Segment and Geographic Information | B5: Years
B6: 2014 | C6: 2015 | D6: 2016 | E6: 2017 | F6: 2018 | H6: key Trends
A7: U.S | B7: 9178.711 | C7: 9063.8751 | D7: 8632.3242 | E7: 8198.5536 | F7: 7665.8
A8: International Lead Markets | B8: 9065.7145 | C8: 8064.1791 | D8: 7555.6764 | E8: 7516.4672 | F8: 7600.1
A9: High Growth Markets | B9: 7262.7572 | C9: 6536.9952 | D9: 6444.0922 | E9: 5665.9968 | F9: 3988.7
A10: Foundational Markets & Corporate | B10: 3608.0366 | C10: 3247.3176 | D10: 3122.4146 | E10: 1987.072 | F10: 1770.6
A11: Total revenues | B11: 29115.219 | C11: 26912.367 | D11: 25754.507 | E11: 23368.09 | F11: =SUM(F7:F10) -> 21025.2
A12: Total revenue growth | B12: - | C12: =(C11-B11)/B11 -> -0.075659822 | D12: =(D11-C11)/C11 -> -0.043023328 | E12: =(E11-D11)/D11 -> -0.0926602 | F12: =(F11-E11)/E11 -> -0.10026021
A13: U.S | B13: 3737.3725 | C13: 3825.108 | D13: 3942.0602 | E13: 4118.9376 | F13: 4015.6
A14: International Lead Markets | B14: 3219.6045 | C14: 2872.6434 | D14: 2968.9664 | E14: 3242.496 | F14: 3485.7
A15: High Growth Markets | B15: 990.8679 | C15: 890.7249 | D15: 1097.0448 | E15: 2049.4336 | F15: 1001.2
A16: Foundational Markets & Corporate | B16: 486.2563 | C16: -21.3918 | D16: 92.6756 | E16: 371.0976 | F16: 320.1
A17: Total operating income | B17: 8434.1012 | C17: 7567.0845 | D17: 8100.747 | E17: 9781.9648 | F17: =SUM(F13:F16) -> 8822.6
A18: total oprating income growth | B18: - | C18: =(C17-B17)/B17 -> -0.10279894 | D18: =(D17-C17)/C17 -> 0.070524189 | E18: =(E17-D17)/D17 -> 0.20753861 | F18: =(F17-E17)/E17 -> -0.098074857
A19: U.S | B19: 12596.298 | C19: 12502.66 | D19: 12510.788 | E19: 12952.166 | F19: 14483.8
A20: International Lead Markets | B20: 13303.242 | C20: 11793.342 | D20: 9531.675 | E20: 12128.563 | F20: 12713
A21: High Growth Markets | B21: 6223.826 | C21: 5558.2674 | D21: 5448.1956 | E21: 4588.2368 | F21: 4404.9
A22: Foundational Markets & Corporate | B22: 4191.9049 | C22: 10322.814 | D22: 4960.3412 | E22: 4946.0224 | F22: 1209.5
A23: Total assets | B23: 36315.271 | C23: 40177.083 | D23: 32450.999 | E23: 34614.989 | F23: =SUM(F19:F22) -> 32811.2
A24: Total assets growth | B24: - | C24: =(C23-B23)/B23 -> 0.10634127 | D24: =(D23-C23)/C23 -> -0.19230077 | E24: =(E23-D23)/D23 -> 0.066684831 | F24: =(F23-E23)/E23 -> -0.05211005
A25: U.S | B25: 781.0021 | C25: 564.6588 | D25: 613.6882 | E25: 881.8688 | F25: 1849.8
A26: International Lead Markets | B26: 840.4181 | C26: 631.2699 | D26: 664.8376 | E26: 527.6672 | F26: 436.4
A27: High Growth Markets | B27: 853.8928 | C27: 572.3895 | D27: 515.8872 | E27: 387.584 | F27: 285.6
A28: Foundational Markets & Corporate | B28: 275.2234 | C28: 152.6019 | D28: 110.4576 | E28: 101.0688 | F28: 169.9
A29: Total capital and expenditure | B29: 2750.5364 | C29: 1920.9201 | D29: 1904.8706 | E29: 1898.1888 | F29: =SUM(F25:F28) -> 2741.7
A30: Total capital and expenditure growth | B30: - | C30: =(C29-B29)/B29 -> -0.30161982 | D30: =(D29-C29)/C29 -> -0.0083551107 | E30: =(E29-D29)/D29 -> -0.0035077448 | F30: =(F29-E29)/E29 -> 0.44437687
A31: U.S | B31: 543.4442 | C31: 545.5968 | D31: 533.7738 | E31: 536.6784 | F31: 598.4
A32: International Lead Markets | B32: 552.9932 | C32: 488.0931 | D32: 472.3736 | E32: 472.1664 | F32: 472.9
A33: High Growth Markets | B33: 411.4558 | C33: 385.3701 | D33: 378.652 | E33: 237.2608 | F33: 233
A34: Foundational Markets & Corporate | B34: 236.9213 | C34: 228.4263 | D34: 201.4596 | E34: 150.016 | F34: 177.7
A35: Total depreciation and amortization | B35: 1744.8145 | C35: 1647.4863 | D35: 1586.259 | E35: 1396.1216 | F35: =SUM(F31:F34) -> 1482
A36: Total depreciation and amortization growth | B36: - | C36: =(C35-B35)/B35 -> -0.055781403 | D36: =(D35-C35)/C35 -> -0.037164072 | E36: =(E35-D35)/D35 -> -0.11986529 | F36: =(F35-E35)/E35 -> 0.06151212 | G36: 1
G37: 1.024
G38: 1.046
A39: Unadjusted values | G39: 1.059
A40: Segment and Geographic Information | B40: Years | G40: 1.061
B41: 2014 | C41: 2015 | D41: 2016 | E41: 2017 | F41: 2018
A42: U.S | B42: 8651 | C42: 8558.9 | D42: 8252.7 | E42: 8006.4 | F42: 7665.8
A43: International Lead Markets | B43: 8544.5 | C43: 7614.9 | D43: 7223.4 | E43: 7340.3 | F43: 7600.1
A44: High Growth Markets | B44: 6845.2 | C44: 6172.8 | D44: 6160.7 | E44: 5533.2 | F44: 3988.7
A45: Foundational Markets & Corporate | B45: 3400.6 | C45: 3066.4 | D45: 2985.1 | E45: 1940.5 | F45: 1770.6
A46: Total revenues | B46: =SUM(B42:B45) -> 27441.3 | C46: =SUM(C42:C45) -> 25413 | D46: =SUM(D42:D45) -> 24621.9 | E46: =SUM(E42:E45) -> 22820.4 | F46: =SUM(F42:F45) -> 21025.2
A47: Total revenue growth | B47: - | C47: =(C46-B46)/B46 -> -0.073914137 | D47: =(D46-C46)/C46 -> -0.031129737 | E47: =(E46-D46)/D46 -> -0.073166571 | F47: =(F46-E46)/E46 -> -0.078666456
A48: U.S | B48: 3522.5 | C48: 3612 | D48: 3768.7 | E48: 4022.4 | F48: 4015.6
A49: International Lead Markets | B49: 3034.5 | C49: 2712.6 | D49: 2838.4 | E49: 3166.5 | F49: 3485.7
A50: High Growth Markets | B50: 933.9 | C50: 841.1 | D50: 1048.8 | E50: 2001.4 | F50: 1001.2
A51: Foundational Markets & Corporate | B51: 458.3 | C51: -20.2 | D51: 88.6 | E51: 362.4 | F51: 320.1
A52: Total operating income | B52: =SUM(B48:B51) -> 7949.2 | C52: =SUM(C48:C51) -> 7145.5 | D52: =SUM(D48:D51) -> 7744.5 | E52: =SUM(E48:E51) -> 9552.7 | F52: =SUM(F48:F51) -> 8822.6
A53: total oprating income growth | B53: - | C53: =(C52-B52)/B52 -> -0.10110451 | D53: =(D52-C52)/C52 -> 0.083828983 | E53: =(E52-D52)/D52 -> 0.23348183 | F53: =(F52-E52)/E52 -> -0.076428654
A54: U.S | B54: 11872.1 | C54: 11806.1 | D54: 11960.6 | E54: 12648.6 | F54: 14483.8
A55: International Lead Markets | B55: 12538.4 | C55: 11136.3 | D55: 9112.5 | E55: 11844.3 | F55: 12713
A56: High Growth Markets | B56: 5866 | C56: 5248.6 | D56: 5208.6 | E56: 4480.7 | F56: 4404.9
A57: Foundational Markets & Corporate | B57: 3950.9 | C57: 9747.7 | D57: 4742.2 | E57: 4830.1 | F57: 1209.5
A58: Total assets | B58: =SUM(B54:B57) -> 34227.4 | C58: =SUM(C54:C57) -> 37938.7 | D58: =SUM(D54:D57) -> 31023.9 | E58: =SUM(E54:E57) -> 33803.7 | F58: =SUM(F54:F57) -> 32811.2
A59: Total assets growth | B59: - | C59: =(C58-B58)/B58 -> 0.10843067 | D59: =(D58-C58)/C58 -> -0.18226244 | E59: =(E58-D58)/D58 -> 0.089601888 | F59: =(F58-E58)/E58 -> -0.029360691
A60: U.S | B60: 736.1 | C60: 533.2 | D60: 586.7 | E60: 861.2 | F60: 1849.8
A61: International Lead Markets | B61: 792.1 | C61: 596.1 | D61: 635.6 | E61: 515.3 | F61: 436.4
A62: High Growth Markets | B62: 804.8 | C62: 540.5 | D62: 493.2 | E62: 378.5 | F62: 285.6
A63: Foundational Markets & Corporate | B63: 259.4 | C63: 144.1 | D63: 105.6 | E63: 98.7 | F63: 169.9
A64: Total capital and expenditure | B64: =SUM(B60:B63) -> 2592.4 | C64: =SUM(C60:C63) -> 1813.9 | D64: =SUM(D60:D63) -> 1821.1 | E64: =SUM(E60:E63) -> 1853.7 | F64: =SUM(F60:F63) -> 2741.7
A65: Total capital and expenditure growth | B65: - | C65: =(C64-B64)/B64 -> -0.30030088 | D65: =(D64-C64)/C64 -> 0.0039693478 | E65: =(E64-D64)/D64 -> 0.017901268 | F65: =(F64-E64)/E64 -> 0.47904192
A66: U.S | B66: 512.2 | C66: 515.2 | D66: 510.3 | E66: 524.1 | F66: 598.4
A67: International Lead Markets | B67: 521.2 | C67: 460.9 | D67: 451.6 | E67: 461.1 | F67: 472.9
A68: High Growth Markets | B68: 387.8 | C68: 363.9 | D68: 362 | E68: 231.7 | F68: 233
A69: Foundational Markets & Corporate | B69: 223.3 | C69: 215.7 | D69: 192.6 | E69: 146.5 | F69: 177.7
A70: Total depreciation and amortization | B70: =SUM(B66:B69) -> 1644.5 | C70: =SUM(C66:C69) -> 1555.7 | D70: =SUM(D66:D69) -> 1516.5 | E70: =SUM(E66:E69) -> 1363.4 | F70: =SUM(F66:F69) -> 1482
A71: Total depreciation and amortization growth | B71: - | C71: =(C70-B70)/B70 -> -0.053998176 | D71: =(D70-C70)/C70 -> -0.02519766 | E71: =(E70-D70)/D70 -> -0.10095615 | F71: =(F70-E70)/E70 -> 0.086988411
A73: Go to References

Sheet Quarterly Data
A1: Quarterly Data (2014-2018)
A2: Go to Home
A3: In millions, (10-Q)
A4: All values in 2018 USD (BLS CPI-U Adjusted)
A5: Quarterly Revenue
A6: Year | B6: Q1 | C6: Q2 | D6: Q3 | E6: Q4 | F6: Total Revenue
A7: 2014 | B7: =B39*$J$11 -> 7107.04 | C7: =C39*$J$11 -> 7617.6633 | D7: =D39*$J$11 -> 7411.2502 | E7: =E39*$J$11 -> 6971.1638 | F7: =F39*$J$11 -> 29107.117
A8: 2015 | B8: =B40*$J$12 -> 6313.14 | C8: =C40*$J$12 -> 6883.9702 | D8: =D40*$J$12 -> 7008.3493 | E8: =E40*$J$12 -> 6718.2726 | F8: =F40*$J$12 -> 26923.732
A9: 2016 | B9: =B41*$J$13 -> 6176.9474 | C9: =C41*$J$13 -> 6554.7478 | D9: =D41*$J$13 -> 6721.206 | E9: =E41*$J$13 -> 6307.7285 | F9: =F41*$J$13 -> 25760.63
A10: 2017 | B10: =B42*$J$14 -> 5814.5326 | C10: =C42*$J$14 -> 6197.4625 | D10: =D42*$J$14 -> 5895.1548 | E10: =E42*$J$14 -> 5470.6332 | F10: =F42*$J$14 -> 23377.783
A11: 2018 | B11: =B43*$J$15 -> 5138.9 | C11: =C43*$J$15 -> 5353.9 | D11: =D43*$J$15 -> 5369.4 | E11: =E43*$J$15 -> 5163 | F11: =F43*$J$15 -> 21025.2 | J11: 1.0607048
J12: 1.0594472
A13: Seasonality factor | J13: 1.0462487
A14: Year | B14: Q1 | C14: Q2 | D14: Q3 | E14: Q4 | F14: Yearly factor | J14: 1.0244248
A15: 2014 | B15: =B7/($F$7/4) -> 0.97667385 | C15: =C7/($F$7/4) -> 1.0468454 | D15: =D7/($F$7/4) -> 1.0184794 | E15: =E7/($F$7/4) -> 0.95800126 | F15: =SUM(B15:E15)/4 -> 1 | J15: 1
A16: 2015 | B16: =B8/($F$8/4) -> 0.93792941 | C16: =C8/($F$8/4) -> 1.0227364 | D16: =D8/($F$8/4) -> 1.0412151 | E16: =E8/($F$8/4) -> 0.99811907 | F16: =SUM(B16:E16)/4 -> 1
A17: 2016 | B17: =B9/($F$9/4) -> 0.95912988 | C17: =C9/($F$9/4) -> 1.0177931 | D17: =D9/($F$9/4) -> 1.04364 | E17: =E9/($F$9/4) -> 0.97943701 | F17: =SUM(B17:E17)/4 -> 1
A18: 2017 | B18: =B10/($F$10/4) -> 0.99488177 | C18: =C10/($F$10/4) -> 1.0604021 | D18: =D10/($F$10/4) -> 1.0086764 | E18: =E10/($F$10/4) -> 0.93603968 | F18: =SUM(B18:E18)/4 -> 1
A19: 2018 | B19: =B11/($F$11/4) -> 0.9776649 | C19: =C11/($F$11/4) -> 1.0185682 | D19: =D11/($F$11/4) -> 1.021517 | E19: =E11/($F$11/4) -> 0.98224987 | F19: =SUM(B19:E19)/4 -> 1
A21: Volatility
A22: Metris | B22: Years
B23: 2014 | D23: 2015 | F23: 2016 | H23: 2017 | J23: 2018
A24: Mean | B24: =SUM(B7:E7)/4 -> 7276.7793 | D24: =SUM(B8:E8)/4 -> 6730.933 | F24: =SUM(B9:E9)/4 -> 6440.1574 | H24: =SUM(B10:E10)/4 -> 5844.4458 | J24: =SUM(B11:E11)/4 -> 5256.3
B25: Deviations | C25: (Deviations)^2 | D25: Deviations | E25: (Deviations)^2 | F25: Deviations | G25: (Deviations)^2 | H25: Deviations | I25: (Deviations)^2 | J25: Deviations | K25: (Deviations)^2
A26: Q1 | B26: =B7-$B$24 -> -169.73928 | C26: =B26^2 -> 28811.422 | D26: =B8-$D$24 -> -417.79301 | E26: =D26^(2) -> 174551 | F26: =B9-$F$24 -> -263.21 | G26: =F26^2 -> 69279.506 | H26: =B10-$H$24 -> -29.913203 | I26: =H26^2 -> 894.79973 | J26: =B11-$J$24 -> -117.4 | K26: =J26^2 -> 13782.76
A27: Q2 | B27: =C7-$B$24 -> 340.88399 | C27: =B27^2 -> 116201.89 | D27: =C8-$D$24 -> 153.03715 | E27: =D27^(2) -> 23420.369 | F27: =C9-$F$24 -> 114.59038 | G27: =F27^2 -> 13130.956 | H27: =C10-$H$24 -> 353.01678 | I27: =H27^2 -> 124620.84 | J27: =C11-$J$24 -> 97.6 | K27: =J27^2 -> 9525.76
A28: Q3 | B28: =D7-$B$24 -> 134.47084 | C28: =B28^2 -> 18082.408 | D28: =D8-$D$24 -> 277.41625 | E28: =D28^(2) -> 76959.777 | F28: =D9-$F$24 -> 281.04854 | G28: =F28^2 -> 78988.284 | H28: =D10-$H$24 -> 50.709026 | I28: =H28^2 -> 2571.4053 | J28: =D11-$J$24 -> 113.1 | K28: =J28^2 -> 12791.61
A29: Q4 | B29: =E7-$B$24 -> -305.61556 | C29: =B29^2 -> 93400.868 | D29: =E8-$D$24 -> -12.660394 | E29: =D29^(2) -> 160.28558 | F29: =E9-$F$24 -> -132.42892 | G29: =F29^2 -> 17537.42 | H29: =E10-$H$24 -> -373.8126 | I29: =H29^2 -> 139735.86 | J29: =E11-$J$24 -> -93.3 | K29: =J29^2 -> 8704.89
A31: Variance | B31: =SUM(C26:C29)/4 -> 64124.148 | D31: =SUM(E26:E29)/4 -> 68772.857 | F31: =SUM(G26:G29)/4 -> 44734.042 | H31: =SUM(I26:I29)/4 -> 66955.727 | J31: =SUM(K26:K29)/4 -> 11201.255
A33: Stnd Dev | B33: =B31^(0.5) -> 253.22746 | D33: =D31^(0.5) -> 262.2458 | F33: =F31^(0.5) -> 211.50424 | H33: =H31^0.5 -> 258.75805 | J33: =J31^0.5 -> 105.83598
A35: Volatility | B35: =(B33/B24) -> 0.034799388 | D35: =(D33/D24) -> 0.038961285 | F35: =F33/F24 -> 0.03284147 | H35: =H33/H24 -> 0.044274181 | J35: =J33/J24 -> 0.020135073
A37: Unadjusted values
A38: Year | B38: Q1 | C38: Q2 | D38: Q3 | E38: Q4 | F38: Total Revenue
A39: 2014 | B39: 6700.3 | C39: 7181.7 | D39: 6987.1 | E39: =F39-(D39+C39+B39) -> 6572.2 | F39: 27441.3
A40: 2015 | B40: 5958.9 | C40: 6497.7 | D40: 6615.1 | E40: =F40-(D40+C40+B40) -> 6341.3 | F40: 25413
A41: 2016 | B41: 5903.9 | C41: 6265 | D41: 6424.1 | E41: =F41-(D41+C41+B41) -> 6028.9 | F41: 24621.9
A42: 2017 | B42: 5675.9 | C42: 6049.7 | D42: 5754.6 | E42: =F42-(D42+C42+B42) -> 5340.2 | F42: 22820.4
A43: 2018 | B43: 5138.9 | C43: 5353.9 | D43: 5369.4 | E43: =F43-(D43+C43+B43) -> 5163 | F43: 21025.2

Sheet Market Research
A1: Market Research
A2: Go to Home
A3: In millions
A4: All values in 2018 USD (BLS CPI-U Adjusted)
A5: Year | B5: Global fast food market | C5: McDonald's total revenue | D5: Revenue Growth (RG) | E5: McDonald's market share | F5: Seasonality Factor | G5: Volatility | H5: Cycle phase
A7: 2014 | B7: 792251.8 | C7: 29107.117 | D7: - | E7: =C7/B7 -> 0.03673973 | F7: 1 | G7: 0.0348 | H7: Expansion. | K7: 1.0607048
A8: 2015 | B8: 849967.1 | C8: 26923.732 | D8: =(C8-C7)/C7 -> -0.075012075 | E8: =C8/B8 -> 0.031676205 | F8: 1 | G8: 0.039 | H8: Expansion. | K8: 1.0594472
A9: 2016 | B9: 884585 | C9: 25760.63 | D9: =(C9-C8)/C8 -> -0.043199893 | E9: =C9/B9 -> 0.029121712 | F9: 1 | G9: 0.0328 | H9: Expansion. | K9: 1.0462487
A10: 2017 | B10: 900356.9 | C10: 23377.783 | D10: =(C10-C9)/C9 -> -0.092499548 | E10: =C10/B10 -> 0.025965018 | F10: 1 | G10: 0.0443 | H10: Expansion. | K10: 1.0244248
A11: 2018 | B11: 906714.2 | C11: 21025.2 | D11: =(C11-C10)/C10 -> -0.10063328 | E11: =C11/B11 -> 0.023188343 | F11: 1 | G11: 0.0201 | H11: Expansion. | K11: 1
A13: Average RG: | B13: =SUM(D8:D11)/4 -> -0.0778362
A15: Unadjusted values
A16: Market size
A17: 2014 | B17: 746910.8
A18: 2015 | B18: 802274.1
A19: 2016 | B19: 845482.6
A20: 2017 | B20: 878890.2
A21: 2018 | B21: 906714.2
A23: Refer below link for market size:
A24: https://www.ibisworld.com/global/market-size/global-fast-food-restaurants/1480/

Sheet Assumed growth
A1: Assumed growth
A2: Go to Home
B100: Refer to the sources provided in the "References" for information : | I100: Go to References

Sheet Forecast
A1: Forecast
A2: Go to Home
A3: In millions
A4: All values in 2018 USD (BLS CPI-U Adjusted)
A6: 1) Baseline Growth | I6: 2) Pandemic Disruption
A7: Assumed CAGR: | C7: 0.04 | I7: Assumed CAGR: | J7: 0.015
A8: Assumed Revenue Growth: | C8: 0.02 | I8: Hindsight scenario: | J8: 0.02
A9: Market size (2018): | C9: 906714.2 | I9: Market size (2018): | J9: 906714.2
A10: Revenue (2018): | C10: 21025.2 | I10: Revenue (2018): | J10: 21025.2
A12: Year | B12: Projected Market size (4%) | C12: Revenue Growth (%) | D12: CPI Multiplier | E12: Projected nominal Revenue | F12: Adjusted Revenue | G12: Market Share (%) | I12: Year | J12: Projected Market size (1.5%) | K12: Hindsight Scenario for Market size (2%) | L12: Revenue Growth (%) | M12: CPI Multiplier | N12: Projected nominal Revenue | O12: Adjusted Revenue | P12: Market Share (%)
A13: 2019 | B13: =C9*1.04 -> 942982.77 | C13: 0.02 | D13: 0.99 | E13: =C10*1.02 -> 21445.704 | F13: =E13/D13 -> 21662.327 | G13: =F13/B13 -> 0.022972135 | I13: 2019 | J13: =J9*1.015 -> 920314.91 | K13: =J9*1.02 -> 924848.48 | L13: 0.05 | M13: 0.99 | N13: =J10*1.05 -> 22076.46 | O13: =N13/M13 -> 22299.455 | P13: =O13/J13 -> 0.024230244
A14: 2020 | B14: =B13*1.04 -> 980702.08 | C14: 0.02 | D14: 0.98 | E14: =E13*1.02 -> 21874.618 | F14: =E14/D14 -> 22321.039 | G14: =F14/B14 -> 0.022760265 | I14: 2020 | J14: =J13*1.015 -> 934119.64 | K14: =K13*1.02 -> 943345.45 | L14: -0.1 | M14: 0.98 | N14: =N13*0.9 -> 19868.814 | O14: =N14/M14 -> 20274.3 | P14: =O14/J14 -> 0.021704179
A15: 2021 | B15: =B14*1.04 -> 1019930.2 | C15: 0.02 | D15: 0.97 | E15: =E14*1.02 -> 22312.11 | F15: =E15/D15 -> 23002.176 | G15: =F15/B15 -> 0.022552697 | I15: 2021 | J15: =J14*1.015 -> 948131.43 | K15: =K14*1.02 -> 962212.36 | L15: -0.14 | M15: 0.97 | N15: =N14*0.86 -> 17087.18 | O15: =N15/M15 -> 17615.65 | P15: =O15/J15 -> 0.018579333
A16: 2022 | B16: =B15*1.04 -> 1060727.4 | C16: 0.02 | D16: 0.96 | E16: =E15*1.02 -> 22758.353 | F16: =E16/D16 -> 23706.617 | G16: =F16/B16 -> 0.022349397 | I16: 2022 | J16: =J15*1.015 -> 962353.4 | K16: =K15*1.02 -> 981456.61 | L16: 0.08 | M16: 0.96 | N16: =N15*1.08 -> 18454.154 | O16: =N16/M16 -> 19223.078 | P16: =O16/J16 -> 0.019975071
A17: 2023 | B17: =B16*1.04 -> 1103156.5 | C17: 0.02 | D17: 0.95 | E17: =E16*1.02 -> 23213.52 | F17: =E17/D17 -> 24435.284 | G17: =F17/B17 -> 0.022150334 | I17: 2023 | J17: =J16*1.015 -> 976788.7 | K17: =K16*1.02 -> 1001085.7 | L17: 0.05 | M17: 0.95 | N17: =N16*1.05 -> 19376.862 | O17: =N17/M17 -> 20396.697 | P17: =O17/J17 -> 0.020881381
A38: Note:
A39: Numbers here use Indian format (like "9,20,314" for 9,203,140) because the Excel setup started with an Indian locale, sticking to 2-3-2 grouping. I tried switching to American style (3-3-3), but it got messy and threw off the graphs—data and visuals didn’t match up. So, I kept the Indian format to keep everything accurate and consistent. All figures still work as intended.

Sheet References
A1: References
A2: Go to Home
A4: McDonald's Annual Reports (10-K):
A5: 2014 | B5: https://www.sec.gov/Archives/edgar/data/0000063908/000006390815000016/mcd-12312014x10k.htm
A6: 2015 | B6: https://www.sec.gov/Archives/edgar/data/0000063908/000006390816000103/mcd-12312015x10k.htm
A7: 2016 | B7: https://www.sec.gov/Archives/edgar/data/0000063908/000006390817000017/mcd-12312016x10k.htm
A8: 2017 | B8: https://www.sec.gov/ix?doc=/Archives/edgar/data/0000063908/000006390818000010/mcd-12312017x10k.htm
A9: 2018 | B9: https://www.sec.gov/ix?doc=/Archives/edgar/data/0000063908/000006390819000010/mcd-12312018x10k.htm
A10: Used in:
A11: Overview | B11: Go to Overview
A12: Balance Sheet | B12: Go to Balance Sheet
A13: CF Statement | B13: Go to CF Statemant
A14: Segment Analysis | B14: Go to Segement Analysis
A16: McDonald's Quarterly data (10-Q):
A17: 2014 (Q1) | B17: https://www.sec.gov/Archives/edgar/data/0000063908/000006390814000032/mcd-3312014x10q.htm
A18: (Q2) | B18: https://www.sec.gov/Archives/edgar/data/0000063908/000006390814000059/mcd-6302014x10q.htm
A19: (Q3) | B19: https://www.sec.gov/Archives/edgar/data/0000063908/000006390814000077/mcd-9302014x10q.htm
A21: 2015 (Q1) | B21: https://www.sec.gov/Archives/edgar/data/0000063908/000006390815000039/mcd-3312015x10q.htm
A22: (Q2) | B22: https://www.sec.gov/Archives/edgar/data/0000063908/000006390815000065/mcd-6302015x10q.htm
A23: (Q3) | B23: https://www.sec.gov/Archives/edgar/data/0000063908/000006390815000081/mcd-9302015x10q.htm
A25: 2016 (Q1) | B25: https://www.sec.gov/Archives/edgar/data/0000063908/000006390816000121/mcd-3312016x10q.htm
A26: (Q2) | B26: https://www.sec.gov/Archives/edgar/data/0000063908/000006390816000142/mcd-6302016x10q.htm
A27: (Q3) | B27: https://www.sec.gov/Archives/edgar/data/0000063908/000006390816000161/mcd-9302016x10q.htm
A29: 2017 (Q1) | B29: https://www.sec.gov/Archives/edgar/data/0000063908/000006390817000025/mcd-3312017x10q.htm
A30: (Q2) | B30: https://www.sec.gov/ix?doc=/Archives/edgar/data/0000063908/000006390817000039/mcd-6302017x10q.htm
A31: (Q3) | B31: https://www.sec.gov/ix?doc=/Archives/edgar/data/0000063908/000006390817000053/mcd-9302017x10q.htm
... A35: (Q3) | B35: https://www.sec.gov/ix?doc=/Archives/edgar/data/0000063908/000006390818000064/mcd-9302018x10q.htm
A36: Used in:
A37: Quarterly Data | B37: Go to Quarterly Data
A39: Consumer Price Index (CPI) by Bureau of Labour Statistics (BLS):
B40: https://www.bls.gov/regions/mid-atlantic/data/consumerpriceindexhistorical_us_table.htm
A41: Used in:
A42: Overview | B42: Go to Overview
A44: Market Capital (2014-2018):
B45: https://stockanalysis.com/stocks/mcd/market-cap/
A46: Used in:
A47: CF Statement | B47: Go to CF Statemant
A49: Global Fast Food Market size:
B50: https://www.ibisworld.com/global/market-size/global-fast-food-restaurants/1480/
A51: Used in:
A52: Market Research | B52: Go to Market Research
A54: Assumed Growth:
A55: 2003 SARS: | B55: https://treasury.gov.au/publication/economic-roundup-winter-2003/the-economic-impact-of-severe-acute-respiratory-syndrome-sars
A56: 2008 Crisis: | B56: https://www.ers.usda.gov/amber-waves/2015/march/recession-had-greater-impact-on-visits-to-sit-down-restaurants-than-fast-food-places/
A57: Used in:
A58: Assumed Growth | B58: Go to Assumed Growth

Sheet Summary
A1: Summary
A2: Go to Home

Sheet Outcome Analysis
A1: Outcome Analysis
A2: Go to Home
A3: In millions
A4: All values in 2025 USD (BLS CPI-U Adjusted)
A14: See adjusted Data Source: | C14: Go to Data Source
A16: Year | B16: Actaul Data | D16: Baseline Projection | F16: Pandemic Disruption | H16: Hindsight Scenario
B17: Global Fast-food market size | C17: Revenues | D17: Global Fast-food market size | E17: Revenues | F17: Global Fast-food market size | G17: Revenues | H17: Global Fast-food market size | I17: Revenues
A18: 2014 | B18: ='Data Source'!B9*'Data Source'!D21 -> 1002263 | C18: ='Data Source'!C9*'Data Source'!D21 -> 36822.871 | D18: 1002263 | E18: 36822.871 | F18: 1002263 | G18: 36822.871 | H18: 1002263 | I18: 36822.871
A19: 2015 | B19: ='Data Source'!B10*'Data Source'!D22 -> 1075278.2 | C19: ='Data Source'!C10*'Data Source'!D22 -> 34060.735 | D19: 1075278.2 | E19: 34060.735 | F19: 1075278.2 | G19: 34060.735 | H19: 1075278.2 | I19: 34060.735
A20: 2016 | B20: ='Data Source'!B11*'Data Source'!D23 -> 1119072 | C20: ='Data Source'!C11*'Data Source'!D23 -> 32589.292 | D20: 1119072 | E20: 32589.292 | F20: 1119072 | G20: 32589.292 | H20: 1119072 | I20: 32589.292
A21: 2017 | B21: ='Data Source'!B12*'Data Source'!D24 -> 1139027.4 | C21: ='Data Source'!C12*'Data Source'!D24 -> 29574.868 | D21: 1139027.4 | E21: 29574.868 | F21: 1139027.4 | G21: 29574.868 | H21: 1139027.4 | I21: 29574.868
A22: 2018 | B22: ='Data Source'!B13*'Data Source'!D25 -> 1147068.8 | C22: ='Data Source'!C13*'Data Source'!D25 -> 26598.624 | D22: ='Data Source'!D13*'Data Source'!D25 -> 1147068.8 | E22: ='Data Source'!E13*'Data Source'!D25 -> 26598.624 | F22: ='Data Source'!F13*'Data Source'!D25 -> 1147068.8 | G22: ='Data Source'!G13*'Data Source'!D25 -> 26598.624 | H22: ='Data Source'!H13*'Data Source'!D25 -> 1147068.8 | I22: ='Data Source'!I13*'Data Source'!D25 -> 26598.624
A23: 2019 | B23: ='Data Source'!B14*'Data Source'!D26 -> 1163230.4 | C23: ='Data Source'!C14*'Data Source'!D26 -> 26189.546 | D23: 1192951.5 | E23: 27404.643 | F23: 1164274.8 | G23: 28210.662 | H23: 1170010.1 | I23: 28210.662
A24: 2020 | B24: ='Data Source'!B15*'Data Source'!D27 -> 1107950.1 | C24: ='Data Source'!C15*'Data Source'!D27 -> 23155.351 | D24: 1240669.6 | E24: 28237.968 | F24: 1181738.9 | G24: 25648.673 | H24: 1193410.3 | I24: 25648.673
A25: 2021 | B25: ='Data Source'!B16*'Data Source'!D28 -> 1175306.8 | C25: ='Data Source'!C16*'Data Source'!D28 -> 26813.957 | D25: 1290296.4 | E25: 29099.663 | F25: 1199465 | G25: 22285.26 | H25: 1217278.6 | I25: 22285.26
A26: 2022 | B26: ='Data Source'!B17*'Data Source'!D29 -> 1128715 | C26: ='Data Source'!C17*'Data Source'!D29 -> 24807.555 | D26: 1341908.2 | E26: 29990.84 | F26: 1217457 | G26: 24318.79 | H26: 1241624.1 | I26: 24318.79
A27: 2023 | B27: ='Data Source'!B18*'Data Source'!D30 -> 1099410.9 | C27: ='Data Source'!C18*'Data Source'!D30 -> 26249.685 | D27: 1395584.5 | E27: 30912.664 | F27: 1235718.8 | G27: 25803.516 | H27: 1266456.6 | I27: 25803.516
A53: Error Analysis
A54: Year | B54: Global Market (Pandemic) | C54: Global Market (Hindsight) | D54: Revenues (Both scenarios)
A56: 2019 | B56: =(F23-B23)/B23 -> 0.00089788006 | C56: =(H23-B23)/B23 -> 0.0058284115 | D56: =(I23-C23)/C23 -> 0.077172629
A57: 2020 | B57: =(F24-B24)/B24 -> 0.066599412 | C57: =(H24-B24)/B24 -> 0.077133663 | D57: =(I24-C24)/C24 -> 0.10767802
A58: 2021 | B58: =(F25-B25)/B25 -> 0.020554844 | C58: =(H25-B25)/B25 -> 0.035711353 | D58: =(I25-C25)/C25 -> -0.16889327
A59: 2022 | B59: =(F26-B26)/B26 -> 0.078622134 | C59: =(H26-B26)/B26 -> 0.10003333 | D59: =(I26-C26)/C26 -> -0.01970229
A60: 2023 | B60: =(F27-B27)/B27 -> 0.12398273 | C60: =(H27-B27)/B27 -> 0.15194114 | D60: =(I27-C27)/C27 -> -0.016997109
A61: Average | B61: =SUM(B56:B60)/5 -> 0.058131401 | C61: =SUM(C56:C60)/5 -> 0.07412958 | D61: =SUM(D56:D60)/5 -> -0.0041484041
A81: Note:
A82: Numbers here use Indian format (like "9,20,314" for 9,203,140) because the Excel setup started with an Indian locale.

Sheet Data Source
A1: Data Source
A2: Go to Outcome Analysis
A3: In millions
A4: All values are adjusted to 2018 USD, except Nominal Data, which is not not adjusted and holds all original values.
A7: Year | B7: Nominal Data | D7: Baseline Projection (2018) | F7: Pandemic Disruption (2018) | H7: Hindsight Scenario (2018)
B8: Global Fast-food market size | C8: Revenues | D8: Global Fast-food market size | E8: Revenues | F8: Global Fast-food market size | G8: Revenues | H8: Global Fast-food market size | I8: Revenues
A9: 2014 | B9: 746910.8 | C9: 27441.3 | D9: 792251.8 | E9: 29107.117 | F9: 792251.8 | G9: 29107.117 | H9: 792251.8 | I9: 29107.117
A10: 2015 | B10: 802274.1 | C10: 25413 | D10: 849967.1 | E10: 26923.732 | F10: 849967.1 | G10: 26923.732 | H10: 849967.1 | I10: 26923.732
A11: 2016 | B11: 845482.6 | C11: 24621.9 | D11: 884585 | E11: 25760.63 | F11: 884585 | G11: 25760.63 | H11: 884585 | I11: 25760.63
A12: 2017 | B12: 878890.2 | C12: 22820.4 | D12: 900356.9 | E12: 23377.783 | F12: 900356.9 | G12: 23377.783 | H12: 900356.9 | I12: 23377.783
A13: 2018 | B13: 906714.2 | C13: 21025.2 | D13: 906714.2 | E13: 21025.2 | F13: 906714.2 | G13: 21025.2 | H13: 906714.2 | I13: 21025.2
A14: 2019 | B14: 936152.4 | C14: 21077 | D14: 942982.77 | E14: 21662.327 | F14: 920314.91 | G14: 22299.455 | H14: 924848.48 | I14: 22299.455
A15: 2020 | B15: 902663 | C15: 18865 | D15: 980702.08 | E15: 22321.039 | F15: 934119.64 | G15: 20274.3 | H15: 943345.45 | I15: 20274.3
A16: 2021 | B16: 1002523.3 | C16: 22872 | D16: 1019930.2 | E16: 23002.176 | F16: 948131.43 | G16: 17615.65 | H16: 962212.36 | I16: 17615.65
A17: 2022 | B17: 1039830.5 | C17: 22854 | D17: 1060727.4 | E17: 23706.617 | F17: 962353.4 | G17: 19223.078 | H17: 981456.61 | I17: 19223.078
A18: 2023 | B18: 1054525.7 | C18: 25178 | D18: 1103156.5 | E18: 24435.284 | F18: 976788.7 | G18: 20396.697 | H18: 1001085.7 | I18: 20396.697
A20: Year | B20: CPI | C20: Multiplier
A21: 2014 | B21: 236.73617 | C21: =$B$31/B21 -> 1.3418778 | D21: 1.3418778
A22: 2015 | B22: 237.017 | C22: =$B$31/B22 -> 1.3402878 | D22: 1.3402878
A23: 2016 | B23: 240.00717 | C23: =$B$31/B23 -> 1.3235896 | D23: 1.3235896
A24: 2017 | B24: 245.11958 | C24: =$B$31/B24 -> 1.2959838 | D24: 1.2959838
A25: 2018 | B25: 251.10683 | C25: =$B$31/B25 -> 1.2650831 | D25: 1.2650831
A26: 2019 | B26: 255.65742 | C26: =$B$31/B26 -> 1.2425652 | D26: 1.2425652
A27: 2020 | B27: 258.81117 | C27: =$B$31/B27 -> 1.2274239 | D27: 1.2274239
A28: 2021 | B28: 270.96975 | C28: =$B$31/B28 -> 1.1723486 | D28: 1.1723486
A29: 2022 | B29: 292.65492 | C29: =$B$31/B29 -> 1.0854798 | D29: 1.0854798
A30: 2023 | B30: 304.70158 | C30: =$B$31/B30 -> 1.0425643 | D30: 1.0425643
A31: 2025 | B31: 317.671 | C31: =$B$31/B31 -> 1 | D31: 1
A34: References:
A35: 2019 | B35: https://www.sec.gov/ix?doc=/Archives/edgar/data/0000063908/000006390820000022/mcd-12312019x10k.htm
A36: 2020 | B36: https://www.sec.gov/ix?doc=/Archives/edgar/data/0000063908/000006390821000013/mcd-20201231.htm
A37: 2021 | B37: https://www.sec.gov/ix?doc=/Archives/edgar/data/0000063908/000006390822000011/mcd-20211231.htm
A38: 2022 | B38: https://www.sec.gov/ix?doc=/Archives/edgar/data/0000063908/000006390823000012/mcd-20221231.htm
A39: 2023 | B39: https://www.sec.gov/ix?doc=/Archives/edgar/data/0000063908/000006390824000072/mcd-20231231.htm
A40: Global Market size | B40: https://www.ibisworld.com/global/market-size/global-fast-food-restaurants/1480/
A41: CPI | B41: https://www.bls.gov/regions/mid-atlantic/data/consumerpriceindexhistorical_us_table.htm
A45: Note:
A46: Numbers here use Indian format (like "9,20,314" for 9,203,140) because the Excel setup started with an Indian locale.

Sheet Conclusion
A1: Conclusion
A2: Go to Home
A16: Note: CPI multipliers are rounded to 3 decimals (following BLS practice), which can cause a small 0.03–0.04% error due to Excel’s precision quirks (e.g., 1.061 might read as 1.060696). I caught this and checked it out—the impact on the results is basically zero, so it's all good.
